{
  "meta": {
    "symbol": "600519",
    "name": "贵州茅台",
    "analysis_time": "2026-02-12T01:07:12.136578",
    "data_start": "2001-08-31",
    "data_end": "2026-02-11",
    "total_months": 294,
    "data_quality_warnings": []
  },
  "score": 6.2,
  "signal": "中性",
  "confidence": 0.68,
  "trend_analysis": {
    "ma_alignment": "空头排列（MA5<MA10<MA20<MA60）",
    "price_vs_ma20": "收盘价位于MA20上方约4.31%",
    "trend_6m": "近6个月上涨3.32%",
    "trend_12m": "近12个月上涨3.80%",
    "trend_judgment": "尽管中长期趋势仍为温和上涨（6/12个月分别+3.32%、+3.80%），但当前月线级别均线系统呈现典型空头排列，MA5至MA60逐级下压，显示中期多头动能尚未扭转。价格虽站上MA20约4.31%，构成短期技术支撑，但MA60（约1569.49）仍远高于现价（1504.33），且持续下行，构成强压制。结合历史走势，该空头排列已延续超12个月（自2024年中起），反映机构持仓调整与估值再平衡压力，趋势反转需等待MA5上穿MA10并站稳MA60，目前尚不具备明确多头结构基础。"
  },
  "momentum": {
    "macd_status": "MACD位于零轴下方，柱状图放大，近期金叉——表明空头动能衰减加速，短期下跌势能趋缓，出现初步止跌信号；但零轴下方金叉属弱势反弹，需观察红柱能否持续放大并推动DIF上穿零轴，否则易演变为诱多陷阱。",
    "rsi_value": 52.15,
    "rsi_status": "中性",
    "kdj_status": "K线上穿D线，短线金叉——KDJ在超卖区（此前STOCHd低至22.97）回升形成金叉，反映抛压阶段性释放，但K值仅34.34、D值24.52，仍处中低位，未进入强势区，属于修复性反弹信号，可持续性依赖量能配合与价格突破阻力。"
  },
  "volatility": {
    "boll_position": "价格位于布林中轨与上轨之间——最新收盘1504.33，中轨1442.18，上轨1585.70，位置处于通道中上区域，显示价格脱离底部区域但尚未触及通道压力，具备一定上行空间，但需警惕接近上轨后的波动率收敛风险。",
    "boll_width": "布林带开口扩大——BBU-BBL由2025年12月的297.01扩大至当前287.04（计算值），实际开口变化平缓，但结合标准差动态，中轨斜率转平、上下轨同步外扩，反映波动率阶段性回升，通常伴随趋势启动或变盘，当前更倾向预示方向选择窗口临近。"
  },
  "volume_analysis": {
    "recent_vs_avg": "近3月量能与年内均量接近（约1.11倍）——2026年1月单月量能达117.5万手（异常放量），但2月回落至57.3万手，近三月（2025-12至2026-02）均量约74万手，略高于全年均量（约67万手），属温和放量，未达突破性水平。",
    "volume_price_relation": "价涨量缩，短线动能需观察——2月11日收盘1504.33较1月30日1401.00上涨7.4%，但成交量由117.5万手锐减至57.3万手（-51%），典型价涨量缩，显示上涨主要由筹码锁定推动，缺乏增量资金共振，持续性存疑，需后续量能验证。"
  },
  "key_levels": {
    "support_1": 1322.01,
    "support_2": 1322.01,
    "resistance_1": 1568.0,
    "resistance_2": 1606.43
  },
  "summary": "贵州茅台月线呈现‘弱多趋势、空头结构、动能初修、量价背离’四维交织特征。中长期涨幅温和（12个月+3.8%），但均线空排持续强化压制逻辑；价格站上MA20提供短期支撑，而MA60（1569.49）与第一压力位1568.0形成双重压制；MACD零下金叉叠加KDJ低位金叉，释放技术性修复信号，但RSI中性（52.15）表明多空未明显倾斜；布林带中上轨运行且开口微扩，波动率回升但未失控；量能方面，1月脉冲放量后迅速萎缩，2月上涨伴随显著缩量，价涨量缩削弱上攻可信度。关键支撑1322.01为强底平台，若失守将确认趋势破位；上方需有效突破1568.0并站稳MA60，方有望扭转空头格局。综合评估：中性偏谨慎，短期博弈反弹，中期仍待结构改善确认。"
}